setup.py
uarango/__init__.py
uarango/graph.py
uarango.egg-info/PKG-INFO
uarango.egg-info/SOURCES.txt
uarango.egg-info/dependency_links.txt
uarango.egg-info/top_level.txt